mkdev/__init__.py
mkdev/__main__.py
mkdev/config_parsing.py
mkdev/help.txt
mkdev/mkdev_help.py
mkdev/config/c++.yaml
mkdev/config/java.yaml
mkdev/config/nix.yaml
mkdev/config/py.yaml
mkdev/config_builder/__init__.py
mkdev/config_builder/cli_config_builder.py
mkdev/config_builder/config_builder.tcss
mkdev/config_builder/edit_dialogue.py
mkdev/config_builder/recipe_form.py
mkdev/config_builder/template_form.py
mkdev-2.0.2.dist-info/LICENSE
mkdev-2.0.2.dist-info/METADATA
mkdev-2.0.2.dist-info/WHEEL
mkdev-2.0.2.dist-info/entry_points.txt
mkdev-2.0.2.dist-info/top_level.txt
mkdev-2.0.2.dist-info/RECORD
